{"skeleton":{"hash":"xdHiGr+Ye4ZG4r0vhcgYfH3UH1o","spine":"3.7.93","width":221.6,"height":249.1,"images":"./images/","audio":"/Volumes/CÔNG VIỆC/JOB/3. FREELANCE/MR. Tuấn/lobby2"},"bones":[{"name":"root"},{"name":"popup","parent":"root","x":-0.31,"y":44.43},{"name":"maubinh_icon2","parent":"root","x":2.17,"y":81.26},{"name":"maubinh_icon1","parent":"root","x":-0.31,"y":61.76},{"name":"light","parent":"root","x":96.22,"y":179.73},{"name":"MẬU BINH","parent":"root","x":-0.11,"y":198.75},{"name":"light2","parent":"root","x":-99.38,"y":20.24},{"name":"light3","parent":"root","x":52.56,"y":72.81},{"name":"light4","parent":"root","x":-53.47,"y":90.63,"scaleX":0.708,"scaleY":0.708},{"name":"light5","parent":"root","x":-20.51,"y":32.72,"scaleX":1.032,"scaleY":1.032},{"name":"light6","parent":"root","x":49.88,"y":107.56,"scaleX":0.77,"scaleY":0.77}],"slots":[{"name":"popup","bone":"popup","attachment":"popup"},{"name":"MẬU BINH","bone":"MẬU BINH","attachment":"MẬU BINH"},{"name":"maubinh_icon2","bone":"maubinh_icon2","attachment":"maubinh_icon2"},{"name":"maubinh_icon1","bone":"maubinh_icon1","attachment":"maubinh_icon1"},{"name":"light","bone":"light","color":"ffffffcf","attachment":"light","blend":"additive"},{"name":"light3","bone":"light3","color":"ffffffcf","attachment":"light","blend":"additive"},{"name":"light5","bone":"light4","color":"ffffffcf","attachment":"light","blend":"additive"},{"name":"light7","bone":"light5","color":"ffffffcf","attachment":"light","blend":"additive"},{"name":"light9","bone":"light6","color":"ffffffcf","attachment":"light","blend":"additive"},{"name":"light4","bone":"light3","color":"ffffffcf","attachment":"light","blend":"additive"},{"name":"light6","bone":"light4","color":"ffffffcf","attachment":"light","blend":"additive"},{"name":"light8","bone":"light5","color":"ffffffcf","attachment":"light","blend":"additive"},{"name":"light10","bone":"light6","color":"ffffffcf","attachment":"light","blend":"additive"},{"name":"light2","bone":"light2","color":"ffffffcf","attachment":"light","blend":"additive"}],"skins":{"default":{"MẬU BINH":{"MẬU BINH":{"x":-0.74,"y":-0.47,"width":105,"height":29}},"light":{"light":{"x":0.15,"y":1.88,"width":26,"height":27}},"light10":{"light":{"x":0.15,"y":1.88,"width":26,"height":27}},"light2":{"light":{"x":0.15,"y":1.88,"width":26,"height":27}},"light3":{"light":{"x":0.15,"y":1.88,"width":26,"height":27}},"light4":{"light":{"x":0.15,"y":1.88,"width":26,"height":27}},"light5":{"light":{"x":0.15,"y":1.88,"width":26,"height":27}},"light6":{"light":{"x":0.15,"y":1.88,"width":26,"height":27}},"light7":{"light":{"x":0.15,"y":1.88,"width":26,"height":27}},"light8":{"light":{"x":0.15,"y":1.88,"width":26,"height":27}},"light9":{"light":{"x":0.15,"y":1.88,"width":26,"height":27}},"maubinh_icon1":{"maubinh_icon1":{"x":-2.86,"y":-7.02,"width":170,"height":127}},"maubinh_icon2":{"maubinh_icon2":{"x":-2.84,"y":20.48,"width":145,"height":143}},"popup":{"popup":{"x":-1.79,"y":75.4,"width":218,"height":241}}}},"animations":{"animation":{"slots":{"light":{"color":[{"time":0,"color":"ffffff00"},{"time":0.6667,"color":"ffffffc1"},{"time":1.3333,"color":"ffffff00"}]},"light2":{"color":[{"time":0,"color":"ffffff00"},{"time":0.6667,"color":"ffffffc1"},{"time":1.3333,"color":"ffffff00"}]},"light3":{"color":[{"time":0,"color":"ffffffe9"},{"time":0.3333,"color":"ffffffee"},{"time":0.6667,"color":"ffffffe9"},{"time":1,"color":"ffffffee"},{"time":1.3333,"color":"ffffffe9"}]},"light5":{"color":[{"time":0,"color":"ffffffe9"},{"time":0.3333,"color":"ffffffee"},{"time":0.6667,"color":"ffffffe9"},{"time":1,"color":"ffffffee"},{"time":1.3333,"color":"ffffffe9"}]},"light7":{"color":[{"time":0,"color":"ffffffe9"},{"time":0.3333,"color":"ffffffee"},{"time":0.6667,"color":"ffffffe9"},{"time":1,"color":"ffffffee"},{"time":1.3333,"color":"ffffffe9"}]},"light9":{"color":[{"time":0,"color":"ffffffe9"},{"time":0.3333,"color":"ffffffee"},{"time":0.6667,"color":"ffffffe9"},{"time":1,"color":"ffffffee"},{"time":1.3333,"color":"ffffffe9"}]}},"bones":{"light":{"translate":[{"time":0,"x":0,"y":0},{"time":1.3333,"x":0,"y":-170}]},"light2":{"translate":[{"time":0,"x":0,"y":0},{"time":1.3333,"x":0,"y":180}]},"maubinh_icon1":{"scale":[{"time":0,"x":1.053,"y":1.053},{"time":0.3333,"x":1.107,"y":1.107},{"time":1,"x":1,"y":1},{"time":1.3333,"x":1.053,"y":1.053}]},"maubinh_icon2":{"rotate":[{"time":0,"angle":0},{"time":0.3333,"angle":10},{"time":0.4333,"angle":-10},{"time":0.5333,"angle":10},{"time":0.6333,"angle":0}]},"light3":{"scale":[{"time":0.3333,"x":1.132,"y":1.132}]},"light4":{"scale":[{"time":0.3333,"x":1.132,"y":1.132}]},"light5":{"scale":[{"time":0.3333,"x":1.132,"y":1.132}]},"light6":{"scale":[{"time":0.3333,"x":1.132,"y":1.132}]}}}}}